[
  {
    "variation": "default",
    "name": "Default",
    "slice_type": "tile_slice",
    "items": [
      {
        "TileContent": [
          {
            "type": "paragraph",
            "text": "Sint in dolor incididunt ad voluptate aliquip est proident ipsum eiusmod. Excepteur est ut commodo irure dolor nostrud esse.",
            "spans": []
          }
        ]
      },
      {
        "TileContent": [
          {
            "type": "paragraph",
            "text": "Aliqua culpa qui ad excepteur. Et ea culpa elit labore sint do. Laboris culpa minim magna.",
            "spans": []
          }
        ]
      }
    ],
    "primary": {}
  }
]